{
  "title": "MySQL — Slow Query & Error Monitoring",
  "description": "Slow queries, lock contention, error trends, and top tables via OpenTelemetry",
  "time_range": { "from": "now-7d", "to": "now" },
  "panels": [
    {
      "type": "metric", "uid": "mysql-kpi-slow",
      "grid": { "x": 0, "y": 0, "w": 12, "h": 5 },
      "dataset": { "type": "esql", "query": "FROM logs-mysql.slowlog.otel-default | STATS `Total Slow Queries` = COUNT(*)" },
      "metrics": [{ "type": "primary", "operation": "value", "column": "Total Slow Queries" }]
    },
    {
      "type": "metric", "uid": "mysql-kpi-avg",
      "grid": { "x": 12, "y": 0, "w": 12, "h": 5 },
      "dataset": { "type": "esql", "query": "FROM logs-mysql.slowlog.otel-default | STATS `Avg Query Time (s)` = AVG(`mysql.slowlog.query_time`)" },
      "metrics": [{ "type": "primary", "operation": "value", "column": "Avg Query Time (s)" }]
    },
    {
      "type": "metric", "uid": "mysql-kpi-max",
      "grid": { "x": 24, "y": 0, "w": 12, "h": 5 },
      "dataset": { "type": "esql", "query": "FROM logs-mysql.slowlog.otel-default | STATS `Max Query Time (s)` = MAX(`mysql.slowlog.query_time`)" },
      "metrics": [{ "type": "primary", "operation": "value", "column": "Max Query Time (s)" }]
    },
    {
      "type": "metric", "uid": "mysql-kpi-errors",
      "grid": { "x": 36, "y": 0, "w": 12, "h": 5 },
      "dataset": { "type": "esql", "query": "FROM logs-mysql.error.otel-default | STATS `DB Errors` = COUNT(*)" },
      "metrics": [{ "type": "primary", "operation": "value", "column": "DB Errors" }]
    },
    {
      "type": "xy", "uid": "mysql-slow-rate",
      "title": "Slow Query Rate by Database",
      "grid": { "x": 0, "y": 5, "w": 24, "h": 11 },
      "layers": [{ "type": "area_stacked",
        "dataset": { "type": "esql", "query": "FROM logs-mysql.slowlog.otel-default | STATS count = COUNT(*) BY bucket = BUCKET(@timestamp, 75, ?_tstart, ?_tend), `db.name`" },
        "x": { "operation": "value", "column": "bucket" },
        "y": [{ "operation": "value", "column": "count" }],
        "breakdown_by": { "operation": "value", "column": "db.name" }
      }]
    },
    {
      "type": "xy", "uid": "mysql-query-time",
      "title": "Avg Query Time by Database (s)",
      "grid": { "x": 24, "y": 5, "w": 24, "h": 11 },
      "layers": [{ "type": "line",
        "dataset": { "type": "esql", "query": "FROM logs-mysql.slowlog.otel-default | STATS avg_time = AVG(`mysql.slowlog.query_time`) BY bucket = BUCKET(@timestamp, 75, ?_tstart, ?_tend), `db.name`" },
        "x": { "operation": "value", "column": "bucket" },
        "y": [{ "operation": "value", "column": "avg_time" }],
        "breakdown_by": { "operation": "value", "column": "db.name" }
      }]
    },
    {
      "type": "xy", "uid": "mysql-top-tables",
      "title": "Top Tables by Slow Query Count",
      "grid": { "x": 0, "y": 16, "w": 24, "h": 11 },
      "layers": [{ "type": "bar_horizontal",
        "dataset": { "type": "esql", "query": "FROM logs-mysql.slowlog.otel-default | STATS count = COUNT(*) BY `db.sql.table` | SORT count DESC | LIMIT 15" },
        "x": { "operation": "value", "column": "db.sql.table" },
        "y": [{ "operation": "value", "column": "count" }]
      }]
    },
    {
      "type": "xy", "uid": "mysql-lock-vs-query",
      "title": "Avg Query vs Lock Time by Database",
      "grid": { "x": 24, "y": 16, "w": 24, "h": 11 },
      "layers": [{ "type": "bar",
        "dataset": { "type": "esql", "query": "FROM logs-mysql.slowlog.otel-default | STATS avg_query = AVG(`mysql.slowlog.query_time`), avg_lock = AVG(`mysql.slowlog.lock_time`) BY `db.name`" },
        "x": { "operation": "value", "column": "db.name" },
        "y": [{ "operation": "value", "column": "avg_query" }, { "operation": "value", "column": "avg_lock" }]
      }]
    },
    {
      "type": "xy", "uid": "mysql-error-trend",
      "title": "Error Log Trend",
      "grid": { "x": 0, "y": 27, "w": 48, "h": 11 },
      "layers": [{ "type": "bar_stacked",
        "dataset": { "type": "esql", "query": "FROM logs-mysql.error.otel-default | STATS count = COUNT(*) BY bucket = BUCKET(@timestamp, 75, ?_tstart, ?_tend), `log.level`" },
        "x": { "operation": "value", "column": "bucket" },
        "y": [{ "operation": "value", "column": "count" }],
        "breakdown_by": { "operation": "value", "column": "log.level" }
      }]
    }
  ]
}
